Metadata-Version: 1.0
Name: FunniestTestPyPi
Version: 0.1.4
Summary: The funniest joke in the world
Home-page: http://github.com/MaxMifkovic/FunniestTestPyPi
Author: Max Mifkovic
Author-email: maxmifkovic@gmail.com
License: MIT
Platform: UNKNOWN
